ztext/__init__.py
ztext/oldcode.py
ztext/ztext.py
ztext/nlpsteps/__init__.py
ztext/nlpsteps/sentimentSocre.py
ztext/nlpsteps/svo.py
ztext/nlpsteps/text_clean.py
ztext/nlpsteps/topicAnalysis.py
ztext-0.0.5.dist-info/LICENSE
ztext-0.0.5.dist-info/METADATA
ztext-0.0.5.dist-info/WHEEL
ztext-0.0.5.dist-info/top_level.txt
ztext-0.0.5.dist-info/RECORD
