Metadata-Version: 2.1
Name: ztext
Version: 0.0.5
Summary: An easy to use NLP tool
Home-page: https://github.com/ZackAnalysis/ztext
Author: Zack Dai
Author-email: zdai@brocku.ca
License: UNKNOWN
Platform: UNKNOWN
Classifier: Programming Language :: Python :: 3
Classifier: License :: OSI Approved :: MIT License
Classifier: Operating System :: OS Independent
Requires-Python: >=3.6
Requires-Dist: IPython
Requires-Dist: bokeh
Requires-Dist: pandas
Requires-Dist: xlrd
Requires-Dist: gensim
Requires-Dist: spacy
Requires-Dist: textacy
Requires-Dist: textblob
Requires-Dist: pyvis
Requires-Dist: pyLDAvis
